LICENSE.txt
MANIFEST.in
README.md
setup.cfg
setup.py
elask/__init__.py
elask/enums.py
elask/generics.py
elask/manager.py
elask/mixins.py
elask/serializers.py
elask/viewsets.py
elask.egg-info/PKG-INFO
elask.egg-info/SOURCES.txt
elask.egg-info/dependency_links.txt
elask.egg-info/entry_points.txt
elask.egg-info/requires.txt
elask.egg-info/top_level.txt
elask/bin/elask-admin.py
elask/conf/templates/app/models.py.template
elask/conf/templates/app/routes.py.template
elask/conf/templates/app/serializers.py.template
elask/conf/templates/app/viewsets.py.template
elask/conf/templates/project/dev.py.template
elask/conf/templates/project/server.py.template
elask/conf/templates/project/zappa_settings.json.template
elask/core/__init__.py
elask/core/management/__init__.py
elask/core/management/base.py
elask/core/management/commands/__init__.py
elask/core/management/commands/help.py
elask/core/management/commands/migrate.py
elask/core/management/commands/shell.py
elask/core/management/commands/startapp.py
elask/core/management/commands/startproject.py
elask/db/__init__.py
elask/db/models.py